airflow_custom_trigger_dv01/__init__.py
airflow_custom_trigger_dv01/dataproc_trigger.py
airflow_custom_trigger_dv01-0.0.2.dist-info/METADATA
airflow_custom_trigger_dv01-0.0.2.dist-info/WHEEL
airflow_custom_trigger_dv01-0.0.2.dist-info/licenses/LICENSE
airflow_custom_trigger_dv01-0.0.2.dist-info/RECORD
